phyprops/__init__.py
phyprops/prop_coolprop.py
phyprops-1.0.7.dist-info/METADATA
phyprops-1.0.7.dist-info/WHEEL
phyprops-1.0.7.dist-info/top_level.txt
phyprops-1.0.7.dist-info/RECORD
