Metadata-Version: 2.1
Name: phyprops
Version: 1.0.7
Summary: The simple interface of CoolProp
Home-page: UNKNOWN
Author: Cheng Maohua
Author-email: cmh@seu.edu.cn
License: UNKNOWN
Platform: Windows
Platform: Linux
Classifier: Programming Language :: Python :: 3
Classifier: Topic :: Software Development :: Libraries :: Python Modules
